archi.cpython-36m-x86_64-linux-gnu.so
archi-0.2.3.dist-info/RECORD
archi-0.2.3.dist-info/METADATA
archi-0.2.3.dist-info/top_level.txt
archi-0.2.3.dist-info/LICENSE
archi-0.2.3.dist-info/WHEEL
archi.libs/libacl-3907442e.so.1.1.0
archi.libs/libz-eb09ad1d.so.1.2.3
archi.libs/liblzma-75668d9c.so.0.0.0
archi.libs/libarchive-3744fb4e.so.17
archi.libs/libattr-46fe1d86.so.1.1.0
archi.libs/libzstd-9cc60b9e.so.1.4.5
archi.libs/liblz4-c29043df.so.1.7.1
