Metadata-Version: 2.1
Name: archi
Version: 0.2.3
Summary: Multi-format archive library based on libarchive
Home-page: https://github.com/whtsky/archi
Author: Wu Haotian
Author-email: whtsky@gmail.com
License: MIT
Keywords: libarchive,archive,compress,compression
Platform: UNKNOWN
Classifier: License :: OSI Approved :: MIT License
Classifier: Intended Audience :: Developers
Classifier: Programming Language :: Cython
Classifier: Programming Language :: Python :: 3
Classifier: Topic :: Software Development :: Libraries
